py3status/__init__.py
py3status/argparsers.py
py3status/autodoc.py
py3status/command.py
py3status/composite.py
py3status/constants.py
py3status/core.py
py3status/docstrings.py
py3status/events.py
py3status/exceptions.py
py3status/formatter.py
py3status/helpers.py
py3status/i3status.py
py3status/module.py
py3status/module_test.py
py3status/output.py
py3status/parse_config.py
py3status/private.py
py3status/profiling.py
py3status/py3.py
py3status/request.py
py3status/screenshots.py
py3status/storage.py
py3status/udev_monitor.py
py3status/util.py
py3status/version.py
py3status/modules/README.md
py3status/modules/__init__.py
py3status/modules/air_quality.py
py3status/modules/apt_updates.py
py3status/modules/arch_updates.py
py3status/modules/async_script.py
py3status/modules/audiosink.py
py3status/modules/aws_bill.py
py3status/modules/backlight.py
py3status/modules/battery_level.py
py3status/modules/bluetooth.py
py3status/modules/check_tcp.py
py3status/modules/clock.py
py3status/modules/cmus.py
py3status/modules/coin_balance.py
py3status/modules/coin_market.py
py3status/modules/conky.py
py3status/modules/deadbeef.py
py3status/modules/dexcom.py
py3status/modules/diskdata.py
py3status/modules/dnf_updates.py
py3status/modules/do_not_disturb.py
py3status/modules/dpms.py
py3status/modules/dropboxd_status.py
py3status/modules/emerge_status.py
py3status/modules/exchange_rate.py
py3status/modules/external_script.py
py3status/modules/file_status.py
py3status/modules/frame.py
py3status/modules/getjson.py
py3status/modules/github.py
py3status/modules/gitlab.py
py3status/modules/glpi.py
py3status/modules/google_calendar.py
py3status/modules/graphite.py
py3status/modules/group.py
py3status/modules/hamster.py
py3status/modules/hddtemp.py
py3status/modules/hueshift.py
py3status/modules/i3block.py
py3status/modules/i3pystatus.py
py3status/modules/icinga2.py
py3status/modules/imap.py
py3status/modules/insync.py
py3status/modules/kdeconnector.py
py3status/modules/keyboard_layout.py
py3status-3.63.dist-info/METADATA
py3status-3.63.dist-info/WHEEL
py3status-3.63.dist-info/entry_points.txt
py3status-3.63.dist-info/licenses/LICENSE
py3status-3.63.dist-info/RECORD
