Metadata-Version: 2.4
Name: py3status
Version: 3.63
Summary: py3status: an extensible i3status wrapper written in python
Project-URL: Download, https://github.com/ultrabug/py3status/tags
Project-URL: Homepage, https://github.com/ultrabug/py3status
Author-email: Ultrabug <ultrabug@ultrabug.net>
License-Expression: BSD-2-Clause
License-File: LICENSE
Classifier: Development Status :: 5 - Production/Stable
Classifier: Environment :: Console
Classifier: Intended Audience :: Developers
Classifier: License :: OSI Approved :: BSD License
Classifier: Operating System :: POSIX :: Linux
Classifier: Programming Language :: Python
Classifier: Programming Language :: Python :: 3
Classifier: Programming Language :: Python :: 3.9
Classifier: Programming Language :: Python :: 3.10
Classifier: Programming Language :: Python :: 3.11
Classifier: Programming Language :: Python :: 3.12
Classifier: Programming Language :: Python :: 3.13
Classifier: Programming Language :: Python :: Implementation :: CPython
Classifier: Topic :: Software Development :: Libraries :: Python Modules
Requires-Python: >=3.9
Requires-Dist: setuptools; python_version >= '3.12'
Provides-Extra: dbus
Requires-Dist: dbus-python==1.3.2; extra == 'dbus'
Requires-Dist: pygobject==3.46.0; extra == 'dbus'
Provides-Extra: udev
Requires-Dist: pyudev>=0.21.0; extra == 'udev'
